prevent_submodule_regression/__init__.py
prevent_submodule_regression/cli.py
prevent_submodule_regression/parser.py
prevent_submodule_regression-0.1.3.dist-info/entry_points.txt
prevent_submodule_regression-0.1.3.dist-info/LICENSE
prevent_submodule_regression-0.1.3.dist-info/WHEEL
prevent_submodule_regression-0.1.3.dist-info/METADATA
prevent_submodule_regression-0.1.3.dist-info/RECORD
