Metadata-Version: 2.1
Name: prevent-submodule-regression
Version: 0.1.3
Summary: Pre-commit hook to prevent accidental submodule regressions
Home-page: https://github.com/erikogan/prevent-submodule-regression
License: MPL-2.0
Keywords: precommit,pre-commit,submodule,regression
Author: Erik Ogan
Author-email: erik@ogan.net
Maintainer: Erik Ogan
Maintainer-email: erik@ogan.net
Requires-Python: >=3.7,<4.0
Classifier: License :: OSI Approved
Classifier: Programming Language :: Python :: 3
Classifier: Programming Language :: Python :: 3.7
Classifier: Programming Language :: Python :: 3.8
Classifier: Programming Language :: Python :: 3.9
Requires-Dist: colorama (>=0.4.3,<0.5.0)
Project-URL: Repository, https://github.com/erikogan/prevent-submodule-regression
